{
	"id": 15,
	"name": "Gradient descent",
	"group": "Game",
	"description": "Multiverse fading...",
	"cols": 12,
	"rows": 12,
	"cells": [
		{
			"coord": { "y": 2, "x": 0 },
			"element": "Emitter",
			"rotation": 90,
			"frozen": true,
			"active": true,
			"energized": true
		},
		{
			"coord": { "y": 2, "x": 2 },
			"element": "BeamSplitter",
			"rotation": 135,
			"frozen": false,
			"active": false,
			"energized": true
		},
		{
			"coord": { "y": 2, "x": 4 },
			"element": "BeamSplitter",
			"rotation": 135,
			"frozen": false,
			"active": false,
			"energized": true
		},
		{
			"coord": { "y": 2, "x": 6 },
			"element": "BeamSplitter",
			"rotation": 135,
			"frozen": false,
			"active": false,
			"energized": true
		},
		{
			"coord": { "y": 2, "x": 8 },
			"element": "BeamSplitter",
			"rotation": 135,
			"frozen": false,
			"active": false,
			"energized": true
		},
		{
			"coord": { "y": 2, "x": 10 },
			"element": "BeamSplitter",
			"rotation": 135,
			"frozen": false,
			"active": true,
			"energized": true
		},
		{
			"coord": { "y": 2, "x": 11 },
			"element": "Detector",
			"rotation": 270,
			"frozen": true,
			"active": false,
			"energized": true
		},
		{
			"coord": { "y": 3, "x": 3 },
			"element": "Rock",
			"rotation": 0,
			"frozen": false,
			"active": false,
			"energized": true
		},
		{
			"coord": { "y": 3, "x": 5 },
			"element": "Rock",
			"rotation": 0,
			"frozen": false,
			"active": false,
			"energized": true
		},
		{
			"coord": { "y": 3, "x": 7 },
			"element": "Rock",
			"rotation": 0,
			"frozen": false,
			"active": false,
			"energized": true
		},
		{
			"coord": { "y": 3, "x": 9 },
			"element": "Rock",
			"rotation": 0,
			"frozen": false,
			"active": false,
			"energized": true
		},
		{
			"coord": { "y": 7, "x": 2 },
			"element": "Rock",
			"rotation": 0,
			"frozen": true,
			"active": false,
			"energized": true
		},
		{
			"coord": { "y": 7, "x": 4 },
			"element": "Rock",
			"rotation": 0,
			"frozen": true,
			"active": false,
			"energized": true
		},
		{
			"coord": { "y": 7, "x": 6 },
			"element": "Rock",
			"rotation": 0,
			"frozen": true,
			"active": false,
			"energized": true
		},
		{
			"coord": { "y": 7, "x": 8 },
			"element": "Rock",
			"rotation": 0,
			"frozen": true,
			"active": false,
			"energized": true
		},
		{
			"coord": { "y": 7, "x": 10 },
			"element": "Rock",
			"rotation": 0,
			"frozen": true,
			"active": false,
			"energized": true
		},
		{
			"coord": { "y": 8, "x": 1 },
			"element": "Detector",
			"rotation": 90,
			"frozen": false,
			"active": false,
			"energized": true
		},
		{
			"coord": { "y": 8, "x": 3 },
			"element": "BeamSplitter",
			"rotation": 135,
			"frozen": false,
			"active": false,
			"energized": true
		},
		{
			"coord": { "y": 8, "x": 5 },
			"element": "BeamSplitter",
			"rotation": 135,
			"frozen": false,
			"active": false,
			"energized": true
		},
		{
			"coord": { "y": 8, "x": 7 },
			"element": "BeamSplitter",
			"rotation": 135,
			"frozen": false,
			"active": false,
			"energized": true
		},
		{
			"coord": { "y": 8, "x": 9 },
			"element": "BeamSplitter",
			"rotation": 135,
			"frozen": false,
			"active": false,
			"energized": true
		},
		{
			"coord": { "y": 8, "x": 11 },
			"element": "Emitter",
			"rotation": 270,
			"frozen": false,
			"active": true,
			"energized": true
		}
	],
	"hints": [],
	"goals": []
}
