{
  "id": 1,
  "name": "The first steps",
  "group": "Classic",
  "description": "",
  "grid": {
    "cols": 10,
    "rows": 10,
    "cells": [
      {
        "coord": { "y": 2, "x": 1 },
        "element": "Laser",
        "rotation": 0,
        "frozen": true,
        "active": true,
        "energized": false
      },
      {
        "coord": { "y": 2, "x": 3 },
        "element": "Mirror",
        "rotation": 135,
        "frozen": false,
        "active": false,
        "energized": false
      },
      {
        "coord": { "y": 2, "x": 4 },
        "element": "Rock",
        "rotation": 0,
        "frozen": true,
        "active": false,
        "energized": false
      },
      {
        "coord": { "y": 2, "x": 7 },
        "element": "Detector",
        "rotation": 270,
        "frozen": true,
        "active": false,
        "energized": false
      },
      {
        "coord": { "y": 5, "x": 3 },
        "element": "Mirror",
        "rotation": 135,
        "frozen": true,
        "active": false,
        "energized": false
      },
      {
        "coord": { "y": 5, "x": 7 },
        "element": "Mirror",
        "rotation": 225,
        "frozen": false,
        "active": false,
        "energized": false
      }
    ]
  },
  "hints": [],
  "goals": []
}
